Crypte/MI_key.py
Crypte/__init__.py
Crypte-1.3.4.dist-info/METADATA
Crypte-1.3.4.dist-info/WHEEL
Crypte-1.3.4.dist-info/top_level.txt
Crypte-1.3.4.dist-info/RECORD
