Metadata-Version: 2.1
Name: Crypte
Version: 1.3.4
Summary: API : https://github.com/mbcraft-exe/Crypte/blob/main/Crypte/OpenSource%20Script/Exemples/Simple.py
Author-email: mbcraft@orange.fr
License: MB INC
Keywords: Chiffre,Crypte
Platform: UNKNOWN
